{"cameraMode":{"drawMode":0,"name":"Shaded","section":"Shading Mode"},"sceneLighting":true,"audioPlay":false,"sceneViewState":{"showFog":true,"showMaterialUpdate":false,"showSkybox":true,"showFlares":true,"showImageEffects":true,"showParticleSystems":true},"in2DMode":false,"pivot":{"x":-63.95167541503906,"y":37.310943603515628,"z":121.31294250488281},"rotation":{"x":0.26052358746528628,"y":0.02953396737575531,"z":0.007973447442054749,"w":-0.9649827480316162},"size":383.5665588378906,"orthographic":false}